[
  {
    "part": "TC58NVG0S3HBAI4",
    "cells": "SLC",
    "vendor": "Kioxia",
    "ce": "",
    "datasheet": "",
    "width": "x8",
    "density": "1G",
    "voltage": "2.7 to 3.6",
    "page_size": "(20Package_SO:TSOP-I-48_18.4x12mm_P0.5mm+128)x8",
    "block_size": "(128K+8K)x8",
    "keywords": "-40 to 85",
    "footprint_default": "Package_BGA:BGA-63_9x11mm_Layout10x12_P0.8mm"
  },
  {
    "part": "TC58NVG0S3HTAx0",
    "cells": "SLC",
    "vendor": "Kioxia",
    "ce": "",
    "datasheet": "",
    "width": "x8",
    "density": "1G",
    "voltage": "2.7 to 3.6",
    "page_size": "(20Package_SO:TSOP-I-48_18.4x12mm_P0.5mm+128)x8",
    "block_size": "(128K+8K)x8",
    "footprint_default": "Package_SO:TSOP-I-48_18.4x12mm_P0.5mm",
    "alias":[
      {
        "name":"TC58NVG0S3HTA00",
        "keywords":"0 70°C",
        "datasheet": "https://business.kioxia.com/info/docget.jsp?did=14827&prodName=TC58NVG0S3HTA00"
      },
      {
        "name":"TC58NVG0S3HTAI0",
        "keywords":"-40 +85°C",
        "datasheet": "https://business.kioxia.com/info/docget.jsp?did=14827&prodName=TC58NVG0S3HTAI0"
      }
    ]
  },
  {
    "part": "TC58NVG1S3HBAI4",
    "cells": "SLC",
    "vendor": "Kioxia",
    "ce": "",
    "datasheet": "",
    "width": "x8",
    "density": "2G",
    "voltage": "2.7 to 3.6",
    "page_size": "(20Package_SO:TSOP-I-48_18.4x12mm_P0.5mm+128)x8",
    "block_size": "(128K+8K)x8",
    "keywords": "-40 to 85",
    "footprint_default": "Package_BGA:BGA-63_9x11mm_Layout10x12_P0.8mm"
  },
  {
    "part": "TC58NVG1S3HTAx0",
    "cells": "SLC",
    "vendor": "Kioxia",
    "ce": "",
    "datasheet": "",
    "width": "x8",
    "density": "2G",
    "voltage": "2.7 to 3.6",
    "page_size": "(20Package_SO:TSOP-I-48_18.4x12mm_P0.5mm+128)x8",
    "block_size": "(128K+8K)x8",
    "footprint_default": "Package_SO:TSOP-I-48_18.4x12mm_P0.5mm",
    "alias":[
      {
        "name":"TC58NVG1S3HTA00",
        "keywords":"0 70°C",
        "datasheet": "https://business.kioxia.com/info/docget.jsp?did=14827&prodName=TC58NVG1S3HTA00"
      },
      {
        "name":"TC58NVG1S3HTAI0",
        "keywords":"-40 +85°C",
        "datasheet": "https://business.kioxia.com/info/docget.jsp?did=14827&prodName=TC58NVG1S3HTAI0"
      }
    ]
  },
  {
    "part": "TC58NVG2S0HBAI4",
    "cells": "SLC",
    "vendor": "Kioxia",
    "ce": "",
    "datasheet": "",
    "width": "x8",
    "density": "4G",
    "voltage": "2.7 to 3.6",
    "page_size": "(4096+256)x8",
    "block_size": "(256K+16K)x8",
    "keywords": "-40 to 85",
    "footprint_default": "Package_BGA:BGA-63_9x11mm_Layout10x12_P0.8mm"
  },
  {
    "part": "TC58NVG2S0HTAx0",
    "cells": "SLC",
    "vendor": "Kioxia",
    "ce": "",
    "datasheet": "",
    "width": "x8",
    "density": "4G",
    "voltage": "2.7 to 3.6",
    "page_size": "(4096+256)x8",
    "block_size": "(256K+16K)x8",
    "footprint_default": "Package_SO:TSOP-I-48_18.4x12mm_P0.5mm",
    "alias":[
      {
        "name":"TC58NVG2S0HTA00",
        "keywords":"0 70°C",
        "datasheet": "https://business.kioxia.com/info/docget.jsp?did=14827&prodName=TC58NVG2S0HTA00"
      },
      {
        "name":"TC58NVG2S0HTAI0",
        "keywords":"-40 +85°C",
        "datasheet": "https://business.kioxia.com/info/docget.jsp?did=14827&prodName=TC58NVG2S0HTAI0"
      }
    ]
  },
  {
    "part": "TC58NYG0S3HBAI4",
    "cells": "SLC",
    "vendor": "Kioxia",
    "ce": "",
    "datasheet": "",
    "width": "x8",
    "density": "1G",
    "voltage": "1.70 to 1.95",
    "page_size": "(20Package_SO:TSOP-I-48_18.4x12mm_P0.5mm+128)x8",
    "block_size": "(128K+8K)x8",
    "keywords": "-40 to 85",
    "footprint_default": "Package_BGA:BGA-63_9x11mm_Layout10x12_P0.8mm"
  },
  {
    "part": "TC58NYG1S3HBAI4",
    "cells": "SLC",
    "vendor": "Kioxia",
    "ce": "",
    "datasheet": "",
    "width": "x8",
    "density": "2G",
    "voltage": "1.70 to 1.95",
    "page_size": "(20Package_SO:TSOP-I-48_18.4x12mm_P0.5mm+128)x8",
    "block_size": "(128K+8K)x8",
    "keywords": "-40 to 85",
    "footprint_default": "Package_BGA:BGA-63_9x11mm_Layout10x12_P0.8mm"
  },
  {
    "part": "TC58NYG2S0HBAI4",
    "cells": "SLC",
    "vendor": "Kioxia",
    "ce": "",
    "datasheet": "",
    "width": "x8",
    "density": "4G",
    "voltage": "1.70 to 1.95",
    "page_size": "(4096+256)x8",
    "block_size": "(256K+16K)x8",
    "keywords": "-40 to 85",
    "footprint_default": "Package_BGA:BGA-63_9x11mm_Layout10x12_P0.8mm"
  },
  {
    "part": "TH58NVG3S0HBAI4",
    "cells": "SLC",
    "vendor": "Kioxia",
    "ce": "",
    "datasheet": "",
    "width": "x8",
    "density": "8G(4Gx2)",
    "voltage": "2.7 to 3.6",
    "page_size": "(4096+256)x8",
    "block_size": "(256K+16K)x8",
    "keywords": "-40 to 85",
    "footprint_default": "Package_BGA:BGA-63_9x11mm_Layout10x12_P0.8mm"
  },
  {
    "part": "TH58NVG3S0HTAx0",
    "cells": "SLC",
    "vendor": "Kioxia",
    "ce": "",
    "datasheet": "",
    "width": "x8",
    "density": "8G(4Gx2)",
    "voltage": "2.7 to 3.6",
    "page_size": "(4096+256)x8",
    "block_size": "(256K+16K)x8",
    "footprint_default": "Package_SO:TSOP-I-48_18.4x12mm_P0.5mm",
    "alias":[
      {
        "name":"TH58NVG3S0HTA00",
        "keywords":"0 70°C",
        "datasheet": "https://business.kioxia.com/info/docget.jsp?did=14827&prodName=TH58NVG3S0HTA00"
      },
      {
        "name":"TH58NVG3S0HTAI0",
        "keywords":"-40 +85°C",
        "datasheet": "https://business.kioxia.com/info/docget.jsp?did=14827&prodName=TH58NVG3S0HTAI0"
      }
    ]
  },
  {
    "part": "TH58NVG4S0HTAx0",
    "cells": "SLC",
    "vendor": "Kioxia",
    "ce": "",
    "datasheet": "",
    "width": "x8",
    "density": "16G(4Gx4)",
    "voltage": "2.7 to 3.6",
    "page_size": "(4096+256)x8",
    "block_size": "(256K+16K)x8",
    "footprint_default": "Package_SO:TSOP-I-48_18.4x12mm_P0.5mm",
    "alias":[
      {
        "name":"TH58NVG4S0HTA20",
        "keywords":"0 70°C",
        "datasheet": "https://business.kioxia.com/info/docget.jsp?did=14827&prodName=TH58NVG4S0HTA20"
      },
      {
        "name":"TH58NVG4S0HTAK0",
        "keywords":"-40 +85°C",
        "datasheet": "https://business.kioxia.com/info/docget.jsp?did=14827&prodName=TH58NVG4S0HTAK0"
      }
    ]
  },
  {
    "part": "TH58NYG3S0HBAI4",
    "cells": "SLC",
    "vendor": "Kioxia",
    "ce": "",
    "datasheet": "",
    "width": "x8",
    "density": "8G(4Gx2)",
    "voltage": "1.70 to 1.95",
    "page_size": "(4096+256)x8",
    "block_size": "(256K+16K)x8",
    "keywords": "-40 to 85",
    "footprint_default": "Package_BGA:BGA-63_9x11mm_Layout10x12_P0.8mm"
  }
 ]